p4b/__init__.py
p4b/core.py
p4b-1.0.3.dist-info/METADATA
p4b-1.0.3.dist-info/WHEEL
p4b-1.0.3.dist-info/entry_points.txt
p4b-1.0.3.dist-info/top_level.txt
p4b-1.0.3.dist-info/RECORD
