Metadata-Version: 2.4
Name: p4b
Version: 1.0.3
Summary: god bless you.
Author: p4b-admin
Requires-Dist: rich==14.0.0
Requires-Dist: keyboard>=0.13.5
Requires-Dist: pyperclip>=1.9.0
Requires-Dist: pillow>=11.2.1
Requires-Dist: pyautogui>=0.9.54
Requires-Dist: setuptools==66.1.1
Requires-Dist: google-generativeai==0.8.5
Requires-Dist: openai==1.83.0
Requires-Dist: pythonw==3.0.3
Requires-Dist: setproctitle==1.3.6
Dynamic: author
Dynamic: requires-dist
Dynamic: summary
